acp/__init__.py
acp/exceptions.py
acp/auth/__init__.py
acp/auth/jwt_validator.py
acp/auth/oauth2_client.py
acp/client/__init__.py
acp/client/acp_client.py
acp/client/auth.py
acp/client/exceptions.py
acp/core/__init__.py
acp/core/json_rpc.py
acp/core/streaming.py
acp/core/validation.py
acp/core/webhooks.py
acp/models/__init__.py
acp/models/generated.py
acp/schemas/acp-schema.yaml
acp/schemas/agent-card.schema.json
acp/server/__init__.py
acp/server/acp_server.py
acp/server/decorators.py
acp/server/middleware.py
acp/utils/__init__.py
acp/utils/agent_card.py
acp/utils/config.py
acp/utils/logging.py
acp/utils/schema.py
acp/utils/testing.py
acp_sdk_python-1.3.0.dist-info/licenses/LICENSE
acp_sdk_python-1.3.0.dist-info/METADATA
acp_sdk_python-1.3.0.dist-info/WHEEL
acp_sdk_python-1.3.0.dist-info/entry_points.txt
acp_sdk_python-1.3.0.dist-info/top_level.txt
acp_sdk_python-1.3.0.dist-info/RECORD
