Metadata-Version: 2.4
Name: acp-sdk-python
Version: 1.3.0
Summary: Python implementation of the Agent Communication Protocol (ACP)
Home-page: https://github.com/MoeinRoghani/acp-sdk-python
Author: Moein Roghani
Author-email: Moein Roghani <moein.roghani@proton.me>
License: Apache-2.0
Project-URL: Homepage, https://acp-protocol.org
Project-URL: Documentation, https://docs.acp-protocol.org
Project-URL: Repository, https://github.com/MoeinRoghani/acp-sdk-python
Project-URL: Bug Tracker, https://github.com/MoeinRoghani/acp-sdk-python/issues
Project-URL: Protocol Specification, https://acp-protocol.org/spec
Classifier: Development Status :: 4 - Beta
Classifier: Intended Audience :: Developers
Classifier: Intended Audience :: System Administrators
Classifier: Intended Audience :: Information Technology
Classifier: License :: OSI Approved :: Apache Software License
Classifier: Operating System :: OS Independent
Classifier: Environment :: Web Environment
Classifier: Environment :: Console
Classifier: Programming Language :: Python :: 3
Classifier: Programming Language :: Python :: 3.8
Classifier: Programming Language :: Python :: 3.9
Classifier: Programming Language :: Python :: 3.10
Classifier: Programming Language :: Python :: 3.11
Classifier: Topic :: Software Development :: Libraries :: Python Modules
Classifier: Topic :: Communications
Classifier: Topic :: Internet :: WWW/HTTP :: HTTP Servers
Classifier: Topic :: Scientific/Engineering :: Artificial Intelligence
Classifier: Topic :: System :: Distributed Computing
Classifier: Topic :: System :: Networking
Classifier: Typing :: Typed
Requires-Python: >=3.8
License-File: LICENSE
Requires-Dist: pydantic>=2.0.0
Requires-Dist: httpx>=0.25.0
Requires-Dist: fastapi>=0.104.0
Requires-Dist: uvicorn[standard]>=0.24.0
Requires-Dist: jsonschema>=4.19.0
Requires-Dist: authlib>=1.2.0
Requires-Dist: python-jose[cryptography]>=3.3.0
Requires-Dist: python-dotenv>=1.0.0
Requires-Dist: typer>=0.9.0
Provides-Extra: server
Requires-Dist: fastapi>=0.104.0; extra == "server"
Requires-Dist: uvicorn[standard]>=0.24.0; extra == "server"
Provides-Extra: client
Requires-Dist: httpx>=0.25.0; extra == "client"
Provides-Extra: dev
Requires-Dist: pytest>=7.0.0; extra == "dev"
Requires-Dist: pytest-asyncio>=0.21.0; extra == "dev"
Requires-Dist: black>=23.0.0; extra == "dev"
Requires-Dist: flake8>=6.0.0; extra == "dev"
Dynamic: author
Dynamic: home-page
Dynamic: license-file
Dynamic: requires-python
